LICENSE
README.md
pyproject.toml
setup.cfg
setup.py
packnow/__init__.py
packnow/__main__.py
packnow/main.py
packnow.egg-info/PKG-INFO
packnow.egg-info/SOURCES.txt
packnow.egg-info/dependency_links.txt
packnow.egg-info/entry_points.txt
packnow.egg-info/requires.txt
packnow.egg-info/top_level.txt