Metadata-Version: 2.1
Name: packnow
Version: 1.7
Summary: Pack everything, now.
Author: AWeirdDev
Author-email: AWeirdDev <aweirdscratcher@gmail.com>
License: MIT License
Project-URL: Homepage, https://github.com/AWeirdScratcher/packnow
Project-URL: Bug Tracker, https://github.com/AWeirdScratcher/packnow/issues
Keywords: pack,packing,packnow
Classifier: Programming Language :: Python :: 3.9
Classifier: License :: OSI Approved :: MIT License
Classifier: Operating System :: OS Independent
Requires-Python: >=3.9
License-File: LICENSE
